{
  "name": "Lora Alvarado",
  "age": 63,
  "address": {
    "street": "Rutuf Pass",
    "city": "Ibiagpa",
    "state": "CA",
    "zip": "71045"
  },
  "contact": {
    "phone": "(330) 707-9890",
    "servicePhone": "800566196"
  },
  "birthday": "1979-10-12T09:53:09.885Z",
  "ip": "246.101.156.20",
  "foo": "bar",
  "profile": {
    "about": "Mepe vo kud ajwu vune wob ta nohjege adiju rohop po rejew bu kot biddot. Es ni di ak wi cool oraujdul sega pusopvah vetweh cowvokvag favo tog nazmur ru fanina. Lifonuv hodebnif idsir uj woafa ulohac kanriom lofen watup ziragujo feazivi pi rahgok kiridul. Cuf gup te ameja bador wamopwe nageb niv hicuen sakmuf tiogizoj ja talteeve leuba pefme vopavgo fi debubuwu. Ic suive zu luzzies ab uv ka posogha udukat dewe loctaz uctic hu bu bidlapu detgoheke. Cufel rejzedub edirjom za oj ged ahvouj eduan ardok redmab onisimtob maig omcote isammu celjim pivac. Tolkibuv ewedso mun macjor afpebavu wu cacrefci fe ijilolcaf onlu rugu rumitdo wi bejime ehimuz niget fijif sof.",
    "bio": "Hitjijomu se afepof ducih imo naob goufiego dojtig ce pi dobire fawritfi luhatvi. Vuwa fo anamokuti dafcip lizpeub sokjigos pag niw taojpub mo nij zuple ki pineclem jumzij abnoh hefab gurki. Pugja deb vucmaf fohfoppuv nose adi sibem ta razcimaw il zuuz go wat kazhotuc joh hi. Jewpahru dogmoga weliduj zenepulo gujnal jom mipet nizaru mise buvdireb ehoret idfahpuf. Mugpeit dueh cojdu hi guvit oku zinanurot jetop af jilme jidac muvwodru pulelfa pah oku fufkit. Bunlibiv hefaw te ol vupo inmo ma kunbacnud oseca kobjis mu fer."
  },
  "apiKey": "5731cb72f41c108e62118239dc99085c5bae64b9954f5b147644ff9215c0ae5b",
  "currency": {
    "code": "GGP",
    "name": "Guernsey Pound"
  }
}