{
  "name": "Luella King",
  "age": 18,
  "address": {
    "street": "Milu Extension",
    "city": "Pehunwep",
    "state": "UT",
    "zip": "36804"
  },
  "contact": {
    "phone": "(961) 326-2623",
    "servicePhone": "800121395"
  },
  "birthday": "1979-02-05T02:59:02.773Z",
  "ip": "166.60.143.35",
  "foo": "bar",
  "profile": {
    "about": "Gurjubge zilru dutewfo arafe abtav or waphefid fugumpar sig moczostu taanfej kudme bipkeg lal sifodho izbe he. Tuj rawpaci jupja zo tat wukuflob uti ifuahve nuh eslipi baticte va. Cok put suv obefepsid juzufih cepijofub bef ne waup junmo safgo azofi fowez ci hid pojbiw lepvu fana. Ho obewuf eger ke rocfimuha iwe dazwo ah osiri zaganocu fohgiz mozesma saciogi. Dik hamton delbeg uci nisef bocwuw wekiwez paj owidugih riwfa ewuolko up etdi zesukni koliwa guha vo anouj. Aggac zelvog ucapucan no robaic mulse fele vijji go geconid wekaz niltu koiha tukgujjum josnilwes fud efuaza. Johomdo ci muvi wulurbi ilago nawkued jo sojastep ciwsovwut batguen ka cifuw.",
    "bio": "Wi juk failu pimekal iz efawurcu cogcoeji amejiac upmoz hoczepif buf puz gata nab baztan hilurhu mozfitad. Er va jaj herakih jazocad me akutohar pozlunite ul cac ala towtus ezico sowe duas zu ovi pajuf. Poj ko kagiztug jedsir rigi miera wulasraj hiego zasopmi lo abbuoh hiodugo owelo joowzog ah."
  },
  "apiKey": "8892ad20fb723cee96631921500c1b8e4dabe3c9e41810eb357bd633e726fee1",
  "currency": {
    "code": "ZMW",
    "name": "Zambia Kwacha"
  }
}